{"summary":{"id":"d00337","province":"山东省","city":"德州市","district":"武城县","count":12,"total_distance_km":48.994,"coordinate_system":"GCJ-02 / Amap","generated_at":"2026-05-07 20:21:46"},"rows":[{"name":"郝王庄镇兽医站","address":"025县道与043乡道交叉口西200米","phone":"13791339918","category":"医疗保健服务;动物医疗场所;兽医站","area":"","lng":116.244901,"lat":37.255259,"amap_id":"B0FFG4B9MG","order":1,"prev_distance_km":0.0,"cumulative_distance_km":0.0,"amap_marker_url":"https://uri.amap.com/marker?position=116.244901,37.255259&name=%E9%83%9D%E7%8E%8B%E5%BA%84%E9%95%87%E5%85%BD%E5%8C%BB%E7%AB%99&src=vetmap&coordinate=gaode&callnative=1"},{"name":"玉亭宠物医院","address":"浩天家园北门西320米","phone":"","category":"医疗保健服务;动物医疗场所;宠物诊所","area":"","lng":116.089936,"lat":37.219915,"amap_id":"B0FFKLOOTB","order":2,"prev_distance_km":14.27,"cumulative_distance_km":14.27,"amap_marker_url":"https://uri.amap.com/marker?position=116.089936,37.219915&name=%E7%8E%89%E4%BA%AD%E5%AE%A0%E7%89%A9%E5%8C%BB%E9%99%A2&src=vetmap&coordinate=gaode&callnative=1"},{"name":"宠一生宠物医院","address":"振华东街60号","phone":"13021219296;19265458268","category":"医疗保健服务;动物医疗场所;宠物诊所","area":"","lng":116.086701,"lat":37.211723,"amap_id":"B0L369AKAX","order":3,"prev_distance_km":0.955,"cumulative_distance_km":15.225,"amap_marker_url":"https://uri.amap.com/marker?position=116.086701,37.211723&name=%E5%AE%A0%E4%B8%80%E7%94%9F%E5%AE%A0%E7%89%A9%E5%8C%BB%E9%99%A2&src=vetmap&coordinate=gaode&callnative=1"},{"name":"哆咪武城宠物诊疗中心","address":"名士家园西1门旁","phone":"","category":"医疗保健服务;动物医疗场所;宠物诊所","area":"广运","lng":116.085664,"lat":37.21437,"amap_id":"B0LRBCO2K0","order":4,"prev_distance_km":0.308,"cumulative_distance_km":15.534,"amap_marker_url":"https://uri.amap.com/marker?position=116.085664,37.214370&name=%E5%93%86%E5%92%AA%E6%AD%A6%E5%9F%8E%E5%AE%A0%E7%89%A9%E8%AF%8A%E7%96%97%E4%B8%AD%E5%BF%83&src=vetmap&coordinate=gaode&callnative=1"},{"name":"武城宠康宠物医院·犬猫专科","address":"学府豪庭北门7号","phone":"17862628868","category":"医疗保健服务;动物医疗场所;宠物诊所","area":"广运","lng":116.081225,"lat":37.217722,"amap_id":"B0LDKCQD5Q","order":5,"prev_distance_km":0.542,"cumulative_distance_km":16.075,"amap_marker_url":"https://uri.amap.com/marker?position=116.081225,37.217722&name=%E6%AD%A6%E5%9F%8E%E5%AE%A0%E5%BA%B7%E5%AE%A0%E7%89%A9%E5%8C%BB%E9%99%A2%C2%B7%E7%8A%AC%E7%8C%AB%E4%B8%93%E7%A7%91&src=vetmap&coordinate=gaode&callnative=1"},{"name":"福宠宠物诊疗中心","address":"b区s-10","phone":"18606403913","category":"医疗保健服务;动物医疗场所;宠物诊所","area":"","lng":116.070587,"lat":37.218696,"amap_id":"B0L0G53CTC","order":6,"prev_distance_km":0.948,"cumulative_distance_km":17.023,"amap_marker_url":"https://uri.amap.com/marker?position=116.070587,37.218696&name=%E7%A6%8F%E5%AE%A0%E5%AE%A0%E7%89%A9%E8%AF%8A%E7%96%97%E4%B8%AD%E5%BF%83&src=vetmap&coordinate=gaode&callnative=1"},{"name":"汪旺宠物医院(武城县店)","address":"金马商城北门","phone":"15206964450","category":"医疗保健服务;动物医疗场所;宠物诊所","area":"广运","lng":116.075448,"lat":37.209708,"amap_id":"B0HKGUGJ9S","order":7,"prev_distance_km":1.088,"cumulative_distance_km":18.112,"amap_marker_url":"https://uri.amap.com/marker?position=116.075448,37.209708&name=%E6%B1%AA%E6%97%BA%E5%AE%A0%E7%89%A9%E5%8C%BB%E9%99%A2%28%E6%AD%A6%E5%9F%8E%E5%8E%BF%E5%BA%97%29&src=vetmap&coordinate=gaode&callnative=1"},{"name":"宠物医院","address":"古贝南路","phone":"","category":"医疗保健服务;动物医疗场所;宠物诊所","area":"","lng":116.085464,"lat":37.199592,"amap_id":"B0FFFHCFIA","order":8,"prev_distance_km":1.433,"cumulative_distance_km":19.544,"amap_marker_url":"https://uri.amap.com/marker?position=116.085464,37.199592&name=%E5%AE%A0%E7%89%A9%E5%8C%BB%E9%99%A2&src=vetmap&coordinate=gaode&callnative=1"},{"name":"永臻动物门诊","address":"兴武路与古贝春大街交汇处路南","phone":"13516306699","category":"医疗保健服务;动物医疗场所;宠物诊所","area":"","lng":116.064465,"lat":37.204823,"amap_id":"B0KRRYNK86","order":9,"prev_distance_km":1.949,"cumulative_distance_km":21.493,"amap_marker_url":"https://uri.amap.com/marker?position=116.064465,37.204823&name=%E6%B0%B8%E8%87%BB%E5%8A%A8%E7%89%A9%E9%97%A8%E8%AF%8A&src=vetmap&coordinate=gaode&callnative=1"},{"name":"大信猪病诊疗中心","address":"李家户商业街东首路北","phone":"13589914581;15315841199","category":"医疗保健服务;动物医疗场所;兽医站","area":"","lng":116.024243,"lat":37.145939,"amap_id":"B0FFG4KXIN","order":10,"prev_distance_km":7.455,"cumulative_distance_km":28.947,"amap_marker_url":"https://uri.amap.com/marker?position=116.024243,37.145939&name=%E5%A4%A7%E4%BF%A1%E7%8C%AA%E7%97%85%E8%AF%8A%E7%96%97%E4%B8%AD%E5%BF%83&src=vetmap&coordinate=gaode&callnative=1"},{"name":"树祥动物疾病防治中心","address":"马营华兴家电西90米","phone":"","category":"医疗保健服务;动物医疗场所;兽医站","area":"","lng":115.967955,"lat":37.224059,"amap_id":"B0FFM95FZK","order":11,"prev_distance_km":10.016,"cumulative_distance_km":38.963,"amap_marker_url":"https://uri.amap.com/marker?position=115.967955,37.224059&name=%E6%A0%91%E7%A5%A5%E5%8A%A8%E7%89%A9%E7%96%BE%E7%97%85%E9%98%B2%E6%B2%BB%E4%B8%AD%E5%BF%83&src=vetmap&coordinate=gaode&callnative=1"},{"name":"香君禽病防治中心","address":"将军路与兴贤街交叉口南160米","phone":"","category":"医疗保健服务;动物医疗场所;兽医站","area":"","lng":115.898611,"lat":37.152743,"amap_id":"B0FFFY4ZPS","order":12,"prev_distance_km":10.031,"cumulative_distance_km":48.994,"amap_marker_url":"https://uri.amap.com/marker?position=115.898611,37.152743&name=%E9%A6%99%E5%90%9B%E7%A6%BD%E7%97%85%E9%98%B2%E6%B2%BB%E4%B8%AD%E5%BF%83&src=vetmap&coordinate=gaode&callnative=1"}]}