{"summary":{"id":"d00334","province":"山东省","city":"德州市","district":"平原县","count":14,"route_count":1,"max_route_clinics":14,"total_distance_km":47.551,"coordinate_system":"GCJ-02 / Amap","generated_at":"2026-05-07 21:27:19"},"routes":[{"id":"r1","name":"第1段","count":14,"total_distance_km":47.551,"rows":[{"name":"平原县王果铺镇兽医站","address":"王杲铺镇卫生院西南侧70米","phone":"13583438828","category":"医疗保健服务;动物医疗场所;兽医站","area":"","lng":116.292378,"lat":37.230305,"amap_id":"B0HA67BPUA","order":1,"prev_distance_km":0.0,"cumulative_distance_km":0.0,"amap_marker_url":"https://uri.amap.com/marker?position=116.292378,37.230305&name=%E5%B9%B3%E5%8E%9F%E5%8E%BF%E7%8E%8B%E6%9E%9C%E9%93%BA%E9%95%87%E5%85%BD%E5%8C%BB%E7%AB%99&src=vetmap&coordinate=gaode&callnative=1","route_id":"r1","route_name":"第1段"},{"name":"宠物兽医","address":"北关牙科东侧","phone":"18315888632","category":"医疗保健服务;动物医疗场所;宠物诊所","area":"","lng":116.278799,"lat":37.155822,"amap_id":"B0GK1GVFHA","order":2,"prev_distance_km":8.369,"cumulative_distance_km":8.369,"amap_marker_url":"https://uri.amap.com/marker?position=116.278799,37.155822&name=%E5%AE%A0%E7%89%A9%E5%85%BD%E5%8C%BB&src=vetmap&coordinate=gaode&callnative=1","route_id":"r1","route_name":"第1段"},{"name":"平原天然动物诊所","address":"平恩公路北侧","phone":"0534-4653999;13792242636;18653477478","category":"医疗保健服务;动物医疗场所;宠物诊所","area":"","lng":116.409969,"lat":37.169695,"amap_id":"B0M6BHGV1D","order":3,"prev_distance_km":11.725,"cumulative_distance_km":20.094,"amap_marker_url":"https://uri.amap.com/marker?position=116.409969,37.169695&name=%E5%B9%B3%E5%8E%9F%E5%A4%A9%E7%84%B6%E5%8A%A8%E7%89%A9%E8%AF%8A%E6%89%80&src=vetmap&coordinate=gaode&callnative=1","route_id":"r1","route_name":"第1段"},{"name":"豪拓宠物院","address":"莲花池西街713西北方向160米","phone":"13869245813","category":"医疗保健服务;动物医疗场所;宠物诊所","area":"","lng":116.421656,"lat":37.161143,"amap_id":"B0FFG8PU5Y","order":4,"prev_distance_km":1.406,"cumulative_distance_km":21.5,"amap_marker_url":"https://uri.amap.com/marker?position=116.421656,37.161143&name=%E8%B1%AA%E6%8B%93%E5%AE%A0%E7%89%A9%E9%99%A2&src=vetmap&coordinate=gaode&callnative=1","route_id":"r1","route_name":"第1段"},{"name":"涛飞宠物医院","address":"莲花池东街与共青团路交叉口东120米","phone":"18405318659","category":"医疗保健服务;动物医疗场所;宠物诊所","area":"","lng":116.432246,"lat":37.160234,"amap_id":"B0L6BGX0VM","order":5,"prev_distance_km":0.944,"cumulative_distance_km":22.444,"amap_marker_url":"https://uri.amap.com/marker?position=116.432246,37.160234&name=%E6%B6%9B%E9%A3%9E%E5%AE%A0%E7%89%A9%E5%8C%BB%E9%99%A2&src=vetmap&coordinate=gaode&callnative=1","route_id":"r1","route_name":"第1段"},{"name":"平原县惠农禽病服务中心","address":"站西街与新华路交叉口东60米","phone":"","category":"医疗保健服务;动物医疗场所;兽医站","area":"","lng":116.437771,"lat":37.17026,"amap_id":"B0FFHEF47U","order":6,"prev_distance_km":1.218,"cumulative_distance_km":23.662,"amap_marker_url":"https://uri.amap.com/marker?position=116.437771,37.170260&name=%E5%B9%B3%E5%8E%9F%E5%8E%BF%E6%83%A0%E5%86%9C%E7%A6%BD%E7%97%85%E6%9C%8D%E5%8A%A1%E4%B8%AD%E5%BF%83&src=vetmap&coordinate=gaode&callnative=1","route_id":"r1","route_name":"第1段"},{"name":"仁豪和韵动物医院","address":"丽水豪庭南区西北门北100米","phone":"","category":"医疗保健服务;动物医疗场所;宠物诊所","area":"","lng":116.443203,"lat":37.158511,"amap_id":"B0L31AUCO2","order":7,"prev_distance_km":1.392,"cumulative_distance_km":25.054,"amap_marker_url":"https://uri.amap.com/marker?position=116.443203,37.158511&name=%E4%BB%81%E8%B1%AA%E5%92%8C%E9%9F%B5%E5%8A%A8%E7%89%A9%E5%8C%BB%E9%99%A2&src=vetmap&coordinate=gaode&callnative=1","route_id":"r1","route_name":"第1段"},{"name":"诚必信动物医院","address":"龙门街道督府花园小区34幢05号商铺","phone":"18315825688","category":"医疗保健服务;动物医疗场所;宠物诊所","area":"","lng":116.443305,"lat":37.156627,"amap_id":"B0FFGP8XCH","order":8,"prev_distance_km":0.21,"cumulative_distance_km":25.264,"amap_marker_url":"https://uri.amap.com/marker?position=116.443305,37.156627&name=%E8%AF%9A%E5%BF%85%E4%BF%A1%E5%8A%A8%E7%89%A9%E5%8C%BB%E9%99%A2&src=vetmap&coordinate=gaode&callnative=1","route_id":"r1","route_name":"第1段"},{"name":"利邦牧业高效无抗动保产品服务中心","address":"兴原西街与平腰公路交叉口东160米","phone":"","category":"医疗保健服务;动物医疗场所;动物医疗场所","area":"","lng":116.432068,"lat":37.154466,"amap_id":"B0L0V9JKDX","order":9,"prev_distance_km":1.024,"cumulative_distance_km":26.288,"amap_marker_url":"https://uri.amap.com/marker?position=116.432068,37.154466&name=%E5%88%A9%E9%82%A6%E7%89%A7%E4%B8%9A%E9%AB%98%E6%95%88%E6%97%A0%E6%8A%97%E5%8A%A8%E4%BF%9D%E4%BA%A7%E5%93%81%E6%9C%8D%E5%8A%A1%E4%B8%AD%E5%BF%83&src=vetmap&coordinate=gaode&callnative=1","route_id":"r1","route_name":"第1段"},{"name":"平原县特大鹅苗发放回收鹅蛋","address":"桃园街道办事处","phone":"17753434886","category":"医疗保健服务;动物医疗场所;兽医站","area":"","lng":116.440024,"lat":37.112255,"amap_id":"B0FFMBFYWY","order":10,"prev_distance_km":4.746,"cumulative_distance_km":31.035,"amap_marker_url":"https://uri.amap.com/marker?position=116.440024,37.112255&name=%E5%B9%B3%E5%8E%9F%E5%8E%BF%E7%89%B9%E5%A4%A7%E9%B9%85%E8%8B%97%E5%8F%91%E6%94%BE%E5%9B%9E%E6%94%B6%E9%B9%85%E8%9B%8B&src=vetmap&coordinate=gaode&callnative=1","route_id":"r1","route_name":"第1段"},{"name":"王庙镇兽医站","address":"德州瑞弘电器有限公司东侧120米","phone":"","category":"医疗保健服务;动物医疗场所;兽医站","area":"","lng":116.412118,"lat":37.039472,"amap_id":"B0KK066O7O","order":11,"prev_distance_km":8.463,"cumulative_distance_km":39.498,"amap_marker_url":"https://uri.amap.com/marker?position=116.412118,37.039472&name=%E7%8E%8B%E5%BA%99%E9%95%87%E5%85%BD%E5%8C%BB%E7%AB%99&src=vetmap&coordinate=gaode&callnative=1","route_id":"r1","route_name":"第1段"},{"name":"张华镇畜牧兽医站","address":"平腰公路与019县道交叉口东北100米","phone":"0534-4640667;13905447089","category":"医疗保健服务;动物医疗场所;兽医站","area":"","lng":116.331325,"lat":37.035781,"amap_id":"B0KDD58N2J","order":12,"prev_distance_km":7.183,"cumulative_distance_km":46.681,"amap_marker_url":"https://uri.amap.com/marker?position=116.331325,37.035781&name=%E5%BC%A0%E5%8D%8E%E9%95%87%E7%95%9C%E7%89%A7%E5%85%BD%E5%8C%BB%E7%AB%99&src=vetmap&coordinate=gaode&callnative=1","route_id":"r1","route_name":"第1段"},{"name":"张华兽药店","address":"平腰公路与019县道交叉口北150米","phone":"13675344773;13905447089","category":"医疗保健服务;动物医疗场所;动物医疗场所","area":"","lng":116.328938,"lat":37.029472,"amap_id":"B0FFFS85L0","order":13,"prev_distance_km":0.733,"cumulative_distance_km":47.414,"amap_marker_url":"https://uri.amap.com/marker?position=116.328938,37.029472&name=%E5%BC%A0%E5%8D%8E%E5%85%BD%E8%8D%AF%E5%BA%97&src=vetmap&coordinate=gaode&callnative=1","route_id":"r1","route_name":"第1段"},{"name":"兽医诊所","address":"张华镇人民政府西南侧100米","phone":"","category":"医疗保健服务;动物医疗场所;宠物诊所","area":"","lng":116.327398,"lat":37.029611,"amap_id":"B0FFM9GOL5","order":14,"prev_distance_km":0.138,"cumulative_distance_km":47.551,"amap_marker_url":"https://uri.amap.com/marker?position=116.327398,37.029611&name=%E5%85%BD%E5%8C%BB%E8%AF%8A%E6%89%80&src=vetmap&coordinate=gaode&callnative=1","route_id":"r1","route_name":"第1段"}]}],"rows":[{"name":"平原县王果铺镇兽医站","address":"王杲铺镇卫生院西南侧70米","phone":"13583438828","category":"医疗保健服务;动物医疗场所;兽医站","area":"","lng":116.292378,"lat":37.230305,"amap_id":"B0HA67BPUA","order":1,"prev_distance_km":0.0,"cumulative_distance_km":0.0,"amap_marker_url":"https://uri.amap.com/marker?position=116.292378,37.230305&name=%E5%B9%B3%E5%8E%9F%E5%8E%BF%E7%8E%8B%E6%9E%9C%E9%93%BA%E9%95%87%E5%85%BD%E5%8C%BB%E7%AB%99&src=vetmap&coordinate=gaode&callnative=1","route_id":"r1","route_name":"第1段","global_order":1},{"name":"宠物兽医","address":"北关牙科东侧","phone":"18315888632","category":"医疗保健服务;动物医疗场所;宠物诊所","area":"","lng":116.278799,"lat":37.155822,"amap_id":"B0GK1GVFHA","order":2,"prev_distance_km":8.369,"cumulative_distance_km":8.369,"amap_marker_url":"https://uri.amap.com/marker?position=116.278799,37.155822&name=%E5%AE%A0%E7%89%A9%E5%85%BD%E5%8C%BB&src=vetmap&coordinate=gaode&callnative=1","route_id":"r1","route_name":"第1段","global_order":2},{"name":"平原天然动物诊所","address":"平恩公路北侧","phone":"0534-4653999;13792242636;18653477478","category":"医疗保健服务;动物医疗场所;宠物诊所","area":"","lng":116.409969,"lat":37.169695,"amap_id":"B0M6BHGV1D","order":3,"prev_distance_km":11.725,"cumulative_distance_km":20.094,"amap_marker_url":"https://uri.amap.com/marker?position=116.409969,37.169695&name=%E5%B9%B3%E5%8E%9F%E5%A4%A9%E7%84%B6%E5%8A%A8%E7%89%A9%E8%AF%8A%E6%89%80&src=vetmap&coordinate=gaode&callnative=1","route_id":"r1","route_name":"第1段","global_order":3},{"name":"豪拓宠物院","address":"莲花池西街713西北方向160米","phone":"13869245813","category":"医疗保健服务;动物医疗场所;宠物诊所","area":"","lng":116.421656,"lat":37.161143,"amap_id":"B0FFG8PU5Y","order":4,"prev_distance_km":1.406,"cumulative_distance_km":21.5,"amap_marker_url":"https://uri.amap.com/marker?position=116.421656,37.161143&name=%E8%B1%AA%E6%8B%93%E5%AE%A0%E7%89%A9%E9%99%A2&src=vetmap&coordinate=gaode&callnative=1","route_id":"r1","route_name":"第1段","global_order":4},{"name":"涛飞宠物医院","address":"莲花池东街与共青团路交叉口东120米","phone":"18405318659","category":"医疗保健服务;动物医疗场所;宠物诊所","area":"","lng":116.432246,"lat":37.160234,"amap_id":"B0L6BGX0VM","order":5,"prev_distance_km":0.944,"cumulative_distance_km":22.444,"amap_marker_url":"https://uri.amap.com/marker?position=116.432246,37.160234&name=%E6%B6%9B%E9%A3%9E%E5%AE%A0%E7%89%A9%E5%8C%BB%E9%99%A2&src=vetmap&coordinate=gaode&callnative=1","route_id":"r1","route_name":"第1段","global_order":5},{"name":"平原县惠农禽病服务中心","address":"站西街与新华路交叉口东60米","phone":"","category":"医疗保健服务;动物医疗场所;兽医站","area":"","lng":116.437771,"lat":37.17026,"amap_id":"B0FFHEF47U","order":6,"prev_distance_km":1.218,"cumulative_distance_km":23.662,"amap_marker_url":"https://uri.amap.com/marker?position=116.437771,37.170260&name=%E5%B9%B3%E5%8E%9F%E5%8E%BF%E6%83%A0%E5%86%9C%E7%A6%BD%E7%97%85%E6%9C%8D%E5%8A%A1%E4%B8%AD%E5%BF%83&src=vetmap&coordinate=gaode&callnative=1","route_id":"r1","route_name":"第1段","global_order":6},{"name":"仁豪和韵动物医院","address":"丽水豪庭南区西北门北100米","phone":"","category":"医疗保健服务;动物医疗场所;宠物诊所","area":"","lng":116.443203,"lat":37.158511,"amap_id":"B0L31AUCO2","order":7,"prev_distance_km":1.392,"cumulative_distance_km":25.054,"amap_marker_url":"https://uri.amap.com/marker?position=116.443203,37.158511&name=%E4%BB%81%E8%B1%AA%E5%92%8C%E9%9F%B5%E5%8A%A8%E7%89%A9%E5%8C%BB%E9%99%A2&src=vetmap&coordinate=gaode&callnative=1","route_id":"r1","route_name":"第1段","global_order":7},{"name":"诚必信动物医院","address":"龙门街道督府花园小区34幢05号商铺","phone":"18315825688","category":"医疗保健服务;动物医疗场所;宠物诊所","area":"","lng":116.443305,"lat":37.156627,"amap_id":"B0FFGP8XCH","order":8,"prev_distance_km":0.21,"cumulative_distance_km":25.264,"amap_marker_url":"https://uri.amap.com/marker?position=116.443305,37.156627&name=%E8%AF%9A%E5%BF%85%E4%BF%A1%E5%8A%A8%E7%89%A9%E5%8C%BB%E9%99%A2&src=vetmap&coordinate=gaode&callnative=1","route_id":"r1","route_name":"第1段","global_order":8},{"name":"利邦牧业高效无抗动保产品服务中心","address":"兴原西街与平腰公路交叉口东160米","phone":"","category":"医疗保健服务;动物医疗场所;动物医疗场所","area":"","lng":116.432068,"lat":37.154466,"amap_id":"B0L0V9JKDX","order":9,"prev_distance_km":1.024,"cumulative_distance_km":26.288,"amap_marker_url":"https://uri.amap.com/marker?position=116.432068,37.154466&name=%E5%88%A9%E9%82%A6%E7%89%A7%E4%B8%9A%E9%AB%98%E6%95%88%E6%97%A0%E6%8A%97%E5%8A%A8%E4%BF%9D%E4%BA%A7%E5%93%81%E6%9C%8D%E5%8A%A1%E4%B8%AD%E5%BF%83&src=vetmap&coordinate=gaode&callnative=1","route_id":"r1","route_name":"第1段","global_order":9},{"name":"平原县特大鹅苗发放回收鹅蛋","address":"桃园街道办事处","phone":"17753434886","category":"医疗保健服务;动物医疗场所;兽医站","area":"","lng":116.440024,"lat":37.112255,"amap_id":"B0FFMBFYWY","order":10,"prev_distance_km":4.746,"cumulative_distance_km":31.035,"amap_marker_url":"https://uri.amap.com/marker?position=116.440024,37.112255&name=%E5%B9%B3%E5%8E%9F%E5%8E%BF%E7%89%B9%E5%A4%A7%E9%B9%85%E8%8B%97%E5%8F%91%E6%94%BE%E5%9B%9E%E6%94%B6%E9%B9%85%E8%9B%8B&src=vetmap&coordinate=gaode&callnative=1","route_id":"r1","route_name":"第1段","global_order":10},{"name":"王庙镇兽医站","address":"德州瑞弘电器有限公司东侧120米","phone":"","category":"医疗保健服务;动物医疗场所;兽医站","area":"","lng":116.412118,"lat":37.039472,"amap_id":"B0KK066O7O","order":11,"prev_distance_km":8.463,"cumulative_distance_km":39.498,"amap_marker_url":"https://uri.amap.com/marker?position=116.412118,37.039472&name=%E7%8E%8B%E5%BA%99%E9%95%87%E5%85%BD%E5%8C%BB%E7%AB%99&src=vetmap&coordinate=gaode&callnative=1","route_id":"r1","route_name":"第1段","global_order":11},{"name":"张华镇畜牧兽医站","address":"平腰公路与019县道交叉口东北100米","phone":"0534-4640667;13905447089","category":"医疗保健服务;动物医疗场所;兽医站","area":"","lng":116.331325,"lat":37.035781,"amap_id":"B0KDD58N2J","order":12,"prev_distance_km":7.183,"cumulative_distance_km":46.681,"amap_marker_url":"https://uri.amap.com/marker?position=116.331325,37.035781&name=%E5%BC%A0%E5%8D%8E%E9%95%87%E7%95%9C%E7%89%A7%E5%85%BD%E5%8C%BB%E7%AB%99&src=vetmap&coordinate=gaode&callnative=1","route_id":"r1","route_name":"第1段","global_order":12},{"name":"张华兽药店","address":"平腰公路与019县道交叉口北150米","phone":"13675344773;13905447089","category":"医疗保健服务;动物医疗场所;动物医疗场所","area":"","lng":116.328938,"lat":37.029472,"amap_id":"B0FFFS85L0","order":13,"prev_distance_km":0.733,"cumulative_distance_km":47.414,"amap_marker_url":"https://uri.amap.com/marker?position=116.328938,37.029472&name=%E5%BC%A0%E5%8D%8E%E5%85%BD%E8%8D%AF%E5%BA%97&src=vetmap&coordinate=gaode&callnative=1","route_id":"r1","route_name":"第1段","global_order":13},{"name":"兽医诊所","address":"张华镇人民政府西南侧100米","phone":"","category":"医疗保健服务;动物医疗场所;宠物诊所","area":"","lng":116.327398,"lat":37.029611,"amap_id":"B0FFM9GOL5","order":14,"prev_distance_km":0.138,"cumulative_distance_km":47.551,"amap_marker_url":"https://uri.amap.com/marker?position=116.327398,37.029611&name=%E5%85%BD%E5%8C%BB%E8%AF%8A%E6%89%80&src=vetmap&coordinate=gaode&callnative=1","route_id":"r1","route_name":"第1段","global_order":14}]}