{"summary":{"id":"d01015","province":"河北省","city":"廊坊市","district":"霸州市","count":35,"total_distance_km":92.071,"coordinate_system":"GCJ-02 / Amap","generated_at":"2026-05-07 20:23:12"},"rows":[{"name":"兽医","address":"106国道与G18荣乌高速出口交叉口北200米","phone":"","category":"医疗保健服务;动物医疗场所;兽医站","area":"","lng":116.363384,"lat":39.207766,"amap_id":"B0H1SSH9NY","order":1,"prev_distance_km":0.0,"cumulative_distance_km":0.0,"amap_marker_url":"https://uri.amap.com/marker?position=116.363384,39.207766&name=%E5%85%BD%E5%8C%BB&src=vetmap&coordinate=gaode&callnative=1"},{"name":"周和鑫宠物门诊(圣泰骏景店)","address":"圣泰骏景南门西100米","phone":"18630605068","category":"医疗保健服务;动物医疗场所;宠物诊所","area":"","lng":116.379409,"lat":39.124131,"amap_id":"B0HBLK726U","order":2,"prev_distance_km":9.402,"cumulative_distance_km":9.402,"amap_marker_url":"https://uri.amap.com/marker?position=116.379409,39.124131&name=%E5%91%A8%E5%92%8C%E9%91%AB%E5%AE%A0%E7%89%A9%E9%97%A8%E8%AF%8A%28%E5%9C%A3%E6%B3%B0%E9%AA%8F%E6%99%AF%E5%BA%97%29&src=vetmap&coordinate=gaode&callnative=1"},{"name":"宠诺宠物医院","address":"书香苑南3门东80米","phone":"15133640564;16630418389","category":"医疗保健服务;动物医疗场所;宠物诊所","area":"","lng":116.391751,"lat":39.12998,"amap_id":"B0KRADBT3H","order":3,"prev_distance_km":1.248,"cumulative_distance_km":10.649,"amap_marker_url":"https://uri.amap.com/marker?position=116.391751,39.129980&name=%E5%AE%A0%E8%AF%BA%E5%AE%A0%E7%89%A9%E5%8C%BB%E9%99%A2&src=vetmap&coordinate=gaode&callnative=1"},{"name":"新汪兴宠物门诊(旺星萌宠总店)","address":"兴华中路2号丽雅苑底商","phone":"13288320829","category":"医疗保健服务;动物医疗场所;宠物诊所","area":"","lng":116.400494,"lat":39.133508,"amap_id":"B0G1P4I1SP","order":4,"prev_distance_km":0.85,"cumulative_distance_km":11.499,"amap_marker_url":"https://uri.amap.com/marker?position=116.400494,39.133508&name=%E6%96%B0%E6%B1%AA%E5%85%B4%E5%AE%A0%E7%89%A9%E9%97%A8%E8%AF%8A%28%E6%97%BA%E6%98%9F%E8%90%8C%E5%AE%A0%E6%80%BB%E5%BA%97%29&src=vetmap&coordinate=gaode&callnative=1"},{"name":"爱康宠物门诊关爱宠物医院霸州分店(兴华中路店)","address":"兴华中路105号","phone":"15531635547","category":"医疗保健服务;动物医疗场所;宠物诊所","area":"兴华中路","lng":116.401625,"lat":39.132454,"amap_id":"B0G0D7BMLJ","order":5,"prev_distance_km":0.152,"cumulative_distance_km":11.652,"amap_marker_url":"https://uri.amap.com/marker?position=116.401625,39.132454&name=%E7%88%B1%E5%BA%B7%E5%AE%A0%E7%89%A9%E9%97%A8%E8%AF%8A%E5%85%B3%E7%88%B1%E5%AE%A0%E7%89%A9%E5%8C%BB%E9%99%A2%E9%9C%B8%E5%B7%9E%E5%88%86%E5%BA%97%28%E5%85%B4%E5%8D%8E%E4%B8%AD%E8%B7%AF%E5%BA%97%29&src=vetmap&coordinate=gaode&callnative=1"},{"name":"宠乐宠物门诊部","address":"益众街隆泰小区北门底商111号","phone":"19803069662","category":"医疗保健服务;动物医疗场所;宠物诊所","area":"兴华中路","lng":116.401609,"lat":39.129835,"amap_id":"B0FFJKZOXR","order":6,"prev_distance_km":0.291,"cumulative_distance_km":11.943,"amap_marker_url":"https://uri.amap.com/marker?position=116.401609,39.129835&name=%E5%AE%A0%E4%B9%90%E5%AE%A0%E7%89%A9%E9%97%A8%E8%AF%8A%E9%83%A8&src=vetmap&coordinate=gaode&callnative=1"},{"name":"宠悦宠物门诊","address":"兴华中路隆泰东门54号","phone":"15075658080;19063050811","category":"医疗保健服务;动物医疗场所;宠物诊所","area":"兴华中路","lng":116.40158,"lat":39.127784,"amap_id":"B0FFMHGS4C","order":7,"prev_distance_km":0.228,"cumulative_distance_km":12.171,"amap_marker_url":"https://uri.amap.com/marker?position=116.401580,39.127784&name=%E5%AE%A0%E6%82%A6%E5%AE%A0%E7%89%A9%E9%97%A8%E8%AF%8A&src=vetmap&coordinate=gaode&callnative=1"},{"name":"悦宠贝爱动物医院","address":"迎宾东道12号","phone":"19061261030","category":"医疗保健服务;动物医疗场所;宠物诊所","area":"","lng":116.397964,"lat":39.124476,"amap_id":"B0K3YXERXO","order":8,"prev_distance_km":0.482,"cumulative_distance_km":12.654,"amap_marker_url":"https://uri.amap.com/marker?position=116.397964,39.124476&name=%E6%82%A6%E5%AE%A0%E8%B4%9D%E7%88%B1%E5%8A%A8%E7%89%A9%E5%8C%BB%E9%99%A2&src=vetmap&coordinate=gaode&callnative=1"},{"name":"宠颐生廊牧动物医院(霸州市分院)","address":"温泉道52号","phone":"0316-7273239","category":"医疗保健服务;动物医疗场所;宠物诊所","area":"","lng":116.391363,"lat":39.121101,"amap_id":"B0FFHC96ZF","order":9,"prev_distance_km":0.682,"cumulative_distance_km":13.336,"amap_marker_url":"https://uri.amap.com/marker?position=116.391363,39.121101&name=%E5%AE%A0%E9%A2%90%E7%94%9F%E5%BB%8A%E7%89%A7%E5%8A%A8%E7%89%A9%E5%8C%BB%E9%99%A2%28%E9%9C%B8%E5%B7%9E%E5%B8%82%E5%88%86%E9%99%A2%29&src=vetmap&coordinate=gaode&callnative=1"},{"name":"佳合宠物诊疗","address":"和泓嘉苑底商8号","phone":"15303163330","category":"医疗保健服务;动物医疗场所;宠物诊所","area":"","lng":116.394966,"lat":39.116936,"amap_id":"B0J3UCYEG4","order":10,"prev_distance_km":0.558,"cumulative_distance_km":13.893,"amap_marker_url":"https://uri.amap.com/marker?position=116.394966,39.116936&name=%E4%BD%B3%E5%90%88%E5%AE%A0%E7%89%A9%E8%AF%8A%E7%96%97&src=vetmap&coordinate=gaode&callnative=1"},{"name":"乐迪宠物门诊","address":"建府路与金康东道交叉口东南50米","phone":"15630697551","category":"医疗保健服务;动物医疗场所;宠物诊所","area":"","lng":116.394238,"lat":39.115501,"amap_id":"B0FFIORP3X","order":11,"prev_distance_km":0.171,"cumulative_distance_km":14.065,"amap_marker_url":"https://uri.amap.com/marker?position=116.394238,39.115501&name=%E4%B9%90%E8%BF%AA%E5%AE%A0%E7%89%A9%E9%97%A8%E8%AF%8A&src=vetmap&coordinate=gaode&callnative=1"},{"name":"霸州兴牧宠物医院·急重症诊疗·眼科·心超·骨科·体外碎石","address":"兴华南路与太平道交叉口北40米","phone":"15931809802;17716585253;18331165253","category":"医疗保健服务;动物医疗场所;宠物诊所","area":"兴华南路","lng":116.394429,"lat":39.096392,"amap_id":"B0JD5765NQ","order":12,"prev_distance_km":2.125,"cumulative_distance_km":16.19,"amap_marker_url":"https://uri.amap.com/marker?position=116.394429,39.096392&name=%E9%9C%B8%E5%B7%9E%E5%85%B4%E7%89%A7%E5%AE%A0%E7%89%A9%E5%8C%BB%E9%99%A2%C2%B7%E6%80%A5%E9%87%8D%E7%97%87%E8%AF%8A%E7%96%97%C2%B7%E7%9C%BC%E7%A7%91%C2%B7%E5%BF%83%E8%B6%85%C2%B7%E9%AA%A8%E7%A7%91%C2%B7%E4%BD%93%E5%A4%96%E7%A2%8E%E7%9F%B3&src=vetmap&coordinate=gaode&callnative=1"},{"name":"南关兽医院","address":"兴华南路与太平道交叉口东北80米","phone":"","category":"医疗保健服务;动物医疗场所;兽医站","area":"兴华南路","lng":116.395225,"lat":39.096775,"amap_id":"B0L0UUW8RF","order":13,"prev_distance_km":0.081,"cumulative_distance_km":16.27,"amap_marker_url":"https://uri.amap.com/marker?position=116.395225,39.096775&name=%E5%8D%97%E5%85%B3%E5%85%BD%E5%8C%BB%E9%99%A2&src=vetmap&coordinate=gaode&callnative=1"},{"name":"朵恩动物医院","address":"裕华街道办事处上东枫景小区3-商-12","phone":"13722654594;15233265047","category":"医疗保健服务;动物医疗场所;宠物诊所","area":"建设东道","lng":116.407706,"lat":39.112335,"amap_id":"B0L0T5AMJF","order":14,"prev_distance_km":2.038,"cumulative_distance_km":18.308,"amap_marker_url":"https://uri.amap.com/marker?position=116.407706,39.112335&name=%E6%9C%B5%E6%81%A9%E5%8A%A8%E7%89%A9%E5%8C%BB%E9%99%A2&src=vetmap&coordinate=gaode&callnative=1"},{"name":"鑫宠宠物门诊","address":"建设东道上东枫景底商鑫宠宠物门诊","phone":"13722654594","category":"医疗保健服务;动物医疗场所;宠物诊所","area":"建设东道","lng":116.407782,"lat":39.112345,"amap_id":"B0FFIK3BXE","order":15,"prev_distance_km":0.007,"cumulative_distance_km":18.315,"amap_marker_url":"https://uri.amap.com/marker?position=116.407782,39.112345&name=%E9%91%AB%E5%AE%A0%E5%AE%A0%E7%89%A9%E9%97%A8%E8%AF%8A&src=vetmap&coordinate=gaode&callnative=1"},{"name":"赵大夫宠物诊所","address":"建设东道1312号","phone":"","category":"医疗保健服务;动物医疗场所;宠物诊所","area":"建设东道","lng":116.412044,"lat":39.112642,"amap_id":"B0FFGAFGDN","order":16,"prev_distance_km":0.369,"cumulative_distance_km":18.684,"amap_marker_url":"https://uri.amap.com/marker?position=116.412044,39.112642&name=%E8%B5%B5%E5%A4%A7%E5%A4%AB%E5%AE%A0%E7%89%A9%E8%AF%8A%E6%89%80&src=vetmap&coordinate=gaode&callnative=1"},{"name":"辛店井齐动物诊所","address":"团结道与741乡道交叉口东140米","phone":"0316-7393258;13832698822","category":"医疗保健服务;动物医疗场所;宠物诊所","area":"","lng":116.455576,"lat":39.153319,"amap_id":"B0GR74FDEU","order":17,"prev_distance_km":5.878,"cumulative_distance_km":24.563,"amap_marker_url":"https://uri.amap.com/marker?position=116.455576,39.153319&name=%E8%BE%9B%E5%BA%97%E4%BA%95%E9%BD%90%E5%8A%A8%E7%89%A9%E8%AF%8A%E6%89%80&src=vetmap&coordinate=gaode&callnative=1"},{"name":"冯大夫动物门诊","address":"京环线与振兴路交叉口西120米","phone":"13833682268","category":"医疗保健服务;动物医疗场所;宠物诊所","area":"","lng":116.523065,"lat":39.114242,"amap_id":"B0FFI32ZR2","order":18,"prev_distance_km":7.264,"cumulative_distance_km":31.827,"amap_marker_url":"https://uri.amap.com/marker?position=116.523065,39.114242&name=%E5%86%AF%E5%A4%A7%E5%A4%AB%E5%8A%A8%E7%89%A9%E9%97%A8%E8%AF%8A&src=vetmap&coordinate=gaode&callnative=1"},{"name":"霸州市仁爱宠物服务医疗诊所","address":"幸福路96号","phone":"17731625142","category":"医疗保健服务;动物医疗场所;宠物诊所","area":"","lng":116.54111,"lat":39.072168,"amap_id":"B0I367A4RK","order":19,"prev_distance_km":4.931,"cumulative_distance_km":36.757,"amap_marker_url":"https://uri.amap.com/marker?position=116.541110,39.072168&name=%E9%9C%B8%E5%B7%9E%E5%B8%82%E4%BB%81%E7%88%B1%E5%AE%A0%E7%89%A9%E6%9C%8D%E5%8A%A1%E5%8C%BB%E7%96%97%E8%AF%8A%E6%89%80&src=vetmap&coordinate=gaode&callnative=1"},{"name":"艾尔斯宠物医疗连锁(廊坊分院)","address":"幸福路96号","phone":"17731625142","category":"医疗保健服务;动物医疗场所;宠物诊所","area":"","lng":116.541091,"lat":39.071891,"amap_id":"B0I367A4YH","order":20,"prev_distance_km":0.031,"cumulative_distance_km":36.788,"amap_marker_url":"https://uri.amap.com/marker?position=116.541091,39.071891&name=%E8%89%BE%E5%B0%94%E6%96%AF%E5%AE%A0%E7%89%A9%E5%8C%BB%E7%96%97%E8%BF%9E%E9%94%81%28%E5%BB%8A%E5%9D%8A%E5%88%86%E9%99%A2%29&src=vetmap&coordinate=gaode&callnative=1"},{"name":"潇潇宠物服务中心","address":"王庄子镇靳家堡村永丰路17号","phone":"","category":"医疗保健服务;动物医疗场所;宠物诊所","area":"","lng":116.5792,"lat":39.056957,"amap_id":"B0L0HZQ7D5","order":21,"prev_distance_km":3.685,"cumulative_distance_km":40.474,"amap_marker_url":"https://uri.amap.com/marker?position=116.579200,39.056957&name=%E6%BD%87%E6%BD%87%E5%AE%A0%E7%89%A9%E6%9C%8D%E5%8A%A1%E4%B8%AD%E5%BF%83&src=vetmap&coordinate=gaode&callnative=1"},{"name":"龙佶宠物门诊","address":"芳津道与胜德路交叉口东200米","phone":"13833682626","category":"医疗保健服务;动物医疗场所;宠物诊所","area":"","lng":116.68555,"lat":39.06991,"amap_id":"B0FFGAASHL","order":22,"prev_distance_km":9.294,"cumulative_distance_km":49.768,"amap_marker_url":"https://uri.amap.com/marker?position=116.685550,39.069910&name=%E9%BE%99%E4%BD%B6%E5%AE%A0%E7%89%A9%E9%97%A8%E8%AF%8A&src=vetmap&coordinate=gaode&callnative=1"},{"name":"冯大夫宠物门诊","address":"胜芳镇胜德路香槟花城商铺B-13a号","phone":"13780468833","category":"医疗保健服务;动物医疗场所;宠物诊所","area":"","lng":116.682912,"lat":39.072433,"amap_id":"B0FFH0DOUQ","order":23,"prev_distance_km":0.361,"cumulative_distance_km":50.129,"amap_marker_url":"https://uri.amap.com/marker?position=116.682912,39.072433&name=%E5%86%AF%E5%A4%A7%E5%A4%AB%E5%AE%A0%E7%89%A9%E9%97%A8%E8%AF%8A&src=vetmap&coordinate=gaode&callnative=1"},{"name":"爱宠宠物门诊","address":"香槟花城东门南110米","phone":"13780468833","category":"医疗保健服务;动物医疗场所;宠物诊所","area":"","lng":116.682827,"lat":39.072709,"amap_id":"B0FFG2ELHV","order":24,"prev_distance_km":0.032,"cumulative_distance_km":50.161,"amap_marker_url":"https://uri.amap.com/marker?position=116.682827,39.072709&name=%E7%88%B1%E5%AE%A0%E5%AE%A0%E7%89%A9%E9%97%A8%E8%AF%8A&src=vetmap&coordinate=gaode&callnative=1"},{"name":"胜芳缘爱动物医院","address":"胜芳镇香槟花园东门底商106-107","phone":"15243318975","category":"医疗保健服务;动物医疗场所;宠物诊所","area":"","lng":116.682649,"lat":39.077981,"amap_id":"B0FFI69WX6","order":25,"prev_distance_km":0.586,"cumulative_distance_km":50.747,"amap_marker_url":"https://uri.amap.com/marker?position=116.682649,39.077981&name=%E8%83%9C%E8%8A%B3%E7%BC%98%E7%88%B1%E5%8A%A8%E7%89%A9%E5%8C%BB%E9%99%A2&src=vetmap&coordinate=gaode&callnative=1"},{"name":"胜芳盛爱动物医院","address":"凤凰城西门底商29-4","phone":"19030466800","category":"医疗保健服务;动物医疗场所;动物医疗场所","area":"","lng":116.705273,"lat":39.083923,"amap_id":"B0KRRUQZR7","order":26,"prev_distance_km":2.062,"cumulative_distance_km":52.809,"amap_marker_url":"https://uri.amap.com/marker?position=116.705273,39.083923&name=%E8%83%9C%E8%8A%B3%E7%9B%9B%E7%88%B1%E5%8A%A8%E7%89%A9%E5%8C%BB%E9%99%A2&src=vetmap&coordinate=gaode&callnative=1"},{"name":"宠兴动物医院","address":"芳济道350号中盛超市旁边","phone":"17736707826","category":"医疗保健服务;动物医疗场所;宠物诊所","area":"","lng":116.699331,"lat":39.085376,"amap_id":"B0I2SCMPH5","order":27,"prev_distance_km":0.538,"cumulative_distance_km":53.347,"amap_marker_url":"https://uri.amap.com/marker?position=116.699331,39.085376&name=%E5%AE%A0%E5%85%B4%E5%8A%A8%E7%89%A9%E5%8C%BB%E9%99%A2&src=vetmap&coordinate=gaode&callnative=1"},{"name":"迅康动物门诊","address":"新兴路与振兴道交叉口南120米","phone":"","category":"医疗保健服务;动物医疗场所;宠物诊所","area":"","lng":116.646457,"lat":39.143455,"amap_id":"B0FFI96LAP","order":28,"prev_distance_km":7.907,"cumulative_distance_km":61.253,"amap_marker_url":"https://uri.amap.com/marker?position=116.646457,39.143455&name=%E8%BF%85%E5%BA%B7%E5%8A%A8%E7%89%A9%E9%97%A8%E8%AF%8A&src=vetmap&coordinate=gaode&callnative=1"},{"name":"英明街动物门诊","address":"新兴路与振兴道交叉口南120米","phone":"","category":"医疗保健服务;动物医疗场所;宠物诊所","area":"","lng":116.646475,"lat":39.143475,"amap_id":"B0L0K7Q838","order":29,"prev_distance_km":0.003,"cumulative_distance_km":61.256,"amap_marker_url":"https://uri.amap.com/marker?position=116.646475,39.143475&name=%E8%8B%B1%E6%98%8E%E8%A1%97%E5%8A%A8%E7%89%A9%E9%97%A8%E8%AF%8A&src=vetmap&coordinate=gaode&callnative=1"},{"name":"艾贝佳宠物门诊","address":"堂胜路与永定道交叉口东北60米","phone":"","category":"医疗保健服务;动物医疗场所;宠物诊所","area":"","lng":116.726761,"lat":39.151037,"amap_id":"B0K6H9DDNG","order":30,"prev_distance_km":6.974,"cumulative_distance_km":68.23,"amap_marker_url":"https://uri.amap.com/marker?position=116.726761,39.151037&name=%E8%89%BE%E8%B4%9D%E4%BD%B3%E5%AE%A0%E7%89%A9%E9%97%A8%E8%AF%8A&src=vetmap&coordinate=gaode&callnative=1"},{"name":"你宠我爱精致宠物美容会馆(张柳店)","address":"兴东路2号","phone":"","category":"医疗保健服务;动物医疗场所;动物医疗场所","area":"","lng":116.739476,"lat":39.120911,"amap_id":"B0L1L7E4D6","order":31,"prev_distance_km":3.525,"cumulative_distance_km":71.755,"amap_marker_url":"https://uri.amap.com/marker?position=116.739476,39.120911&name=%E4%BD%A0%E5%AE%A0%E6%88%91%E7%88%B1%E7%B2%BE%E8%87%B4%E5%AE%A0%E7%89%A9%E7%BE%8E%E5%AE%B9%E4%BC%9A%E9%A6%86%28%E5%BC%A0%E6%9F%B3%E5%BA%97%29&src=vetmap&coordinate=gaode&callnative=1"},{"name":"爱宠宠物","address":"霸杨线与振兴路交叉口西220米","phone":"","category":"购物服务;专卖店;宠物用品店|医疗保健服务;动物医疗场所;动物医疗场所","area":"","lng":116.771925,"lat":39.114975,"amap_id":"B0LDM7EHOG","order":32,"prev_distance_km":2.876,"cumulative_distance_km":74.631,"amap_marker_url":"https://uri.amap.com/marker?position=116.771925,39.114975&name=%E7%88%B1%E5%AE%A0%E5%AE%A0%E7%89%A9&src=vetmap&coordinate=gaode&callnative=1"},{"name":"信宠宠物","address":"西外环与吉庆胡同交叉口北140米","phone":"","category":"医疗保健服务;动物医疗场所;动物医疗场所","area":"","lng":116.781296,"lat":39.074328,"amap_id":"B0JUJGL1TX","order":33,"prev_distance_km":4.592,"cumulative_distance_km":79.223,"amap_marker_url":"https://uri.amap.com/marker?position=116.781296,39.074328&name=%E4%BF%A1%E5%AE%A0%E5%AE%A0%E7%89%A9&src=vetmap&coordinate=gaode&callnative=1"},{"name":"大嘴狗宠物诊所(和平路店)","address":"和平路与735乡道交叉口西140米","phone":"13333168596;15132658464","category":"医疗保健服务;动物医疗场所;宠物诊所","area":"","lng":116.822953,"lat":39.128198,"amap_id":"B0GRLYJNKL","order":34,"prev_distance_km":6.986,"cumulative_distance_km":86.209,"amap_marker_url":"https://uri.amap.com/marker?position=116.822953,39.128198&name=%E5%A4%A7%E5%98%B4%E7%8B%97%E5%AE%A0%E7%89%A9%E8%AF%8A%E6%89%80%28%E5%92%8C%E5%B9%B3%E8%B7%AF%E5%BA%97%29&src=vetmap&coordinate=gaode&callnative=1"},{"name":"喵喵宠物诊所","address":"霸杨线与兴港道交叉口南60米","phone":"","category":"医疗保健服务;动物医疗场所;宠物诊所","area":"","lng":116.888907,"lat":39.115479,"amap_id":"B0L1AOKN4S","order":35,"prev_distance_km":5.863,"cumulative_distance_km":92.071,"amap_marker_url":"https://uri.amap.com/marker?position=116.888907,39.115479&name=%E5%96%B5%E5%96%B5%E5%AE%A0%E7%89%A9%E8%AF%8A%E6%89%80&src=vetmap&coordinate=gaode&callnative=1"}]}