{"summary":{"id":"d01236","province":"河南省","city":"济源市","district":"济源市","count":18,"total_distance_km":54.898,"coordinate_system":"GCJ-02 / Amap","generated_at":"2026-05-07 19:57:41"},"rows":[{"name":"世纪动物医院","address":"梨林镇梨林大街西段183号","phone":"","category":"医疗保健服务;动物医疗场所;宠物诊所","area":"","lng":112.708869,"lat":35.076549,"amap_id":"B0KAKZPUHK","order":1,"prev_distance_km":0.0,"cumulative_distance_km":0.0,"amap_marker_url":"https://uri.amap.com/marker?position=112.708869,35.076549&name=%E4%B8%96%E7%BA%AA%E5%8A%A8%E7%89%A9%E5%8C%BB%E9%99%A2&src=vetmap&coordinate=gaode&callnative=1"},{"name":"牧专专业畜禽服务部","address":"梨林镇梨苑广场对面","phone":"13938176383;15803910517","category":"医疗保健服务;动物医疗场所;兽医站","area":"","lng":112.707892,"lat":35.076742,"amap_id":"B0FFG1GYV6","order":2,"prev_distance_km":0.091,"cumulative_distance_km":0.091,"amap_marker_url":"https://uri.amap.com/marker?position=112.707892,35.076742&name=%E7%89%A7%E4%B8%93%E4%B8%93%E4%B8%9A%E7%95%9C%E7%A6%BD%E6%9C%8D%E5%8A%A1%E9%83%A8&src=vetmap&coordinate=gaode&callnative=1"},{"name":"济源市瑞欣畜禽服务部","address":"辛庄南街与208国道交叉口西北20米","phone":"13346787838","category":"医疗保健服务;动物医疗场所;兽医站","area":"","lng":112.689386,"lat":35.130377,"amap_id":"B0G1GXRI1D","order":3,"prev_distance_km":6.197,"cumulative_distance_km":6.288,"amap_marker_url":"https://uri.amap.com/marker?position=112.689386,35.130377&name=%E6%B5%8E%E6%BA%90%E5%B8%82%E7%91%9E%E6%AC%A3%E7%95%9C%E7%A6%BD%E6%9C%8D%E5%8A%A1%E9%83%A8&src=vetmap&coordinate=gaode&callnative=1"},{"name":"牧专畜禽服务部","address":"锡海线","phone":"15803915649","category":"医疗保健服务;动物医疗场所;兽医站","area":"","lng":112.689506,"lat":35.130779,"amap_id":"B0FFLA8121","order":4,"prev_distance_km":0.046,"cumulative_distance_km":6.334,"amap_marker_url":"https://uri.amap.com/marker?position=112.689506,35.130779&name=%E7%89%A7%E4%B8%93%E7%95%9C%E7%A6%BD%E6%9C%8D%E5%8A%A1%E9%83%A8&src=vetmap&coordinate=gaode&callnative=1"},{"name":"济源市玉泉爱康动物医院","address":"沁园北路","phone":"0391-6603120","category":"医疗保健服务;动物医疗场所;兽医站","area":"","lng":112.608665,"lat":35.106036,"amap_id":"B056F00AB4","order":5,"prev_distance_km":7.851,"cumulative_distance_km":14.185,"amap_marker_url":"https://uri.amap.com/marker?position=112.608665,35.106036&name=%E6%B5%8E%E6%BA%90%E5%B8%82%E7%8E%89%E6%B3%89%E7%88%B1%E5%BA%B7%E5%8A%A8%E7%89%A9%E5%8C%BB%E9%99%A2&src=vetmap&coordinate=gaode&callnative=1"},{"name":"济源市动物疫病预防控制中心","address":"沁园路东(家和花园附近)","phone":"","category":"医疗保健服务;动物医疗场所;动物医疗场所","area":"","lng":112.608639,"lat":35.105769,"amap_id":"B056F009G1","order":6,"prev_distance_km":0.03,"cumulative_distance_km":14.215,"amap_marker_url":"https://uri.amap.com/marker?position=112.608639,35.105769&name=%E6%B5%8E%E6%BA%90%E5%B8%82%E5%8A%A8%E7%89%A9%E7%96%AB%E7%97%85%E9%A2%84%E9%98%B2%E6%8E%A7%E5%88%B6%E4%B8%AD%E5%BF%83&src=vetmap&coordinate=gaode&callnative=1"},{"name":"肉星人宠物诊所","address":"北海大道东街商住楼2号","phone":"15837999384;18239071120","category":"医疗保健服务;动物医疗场所;宠物诊所","area":"","lng":112.600787,"lat":35.096559,"amap_id":"B0FFIMEUT1","order":7,"prev_distance_km":1.249,"cumulative_distance_km":15.464,"amap_marker_url":"https://uri.amap.com/marker?position=112.600787,35.096559&name=%E8%82%89%E6%98%9F%E4%BA%BA%E5%AE%A0%E7%89%A9%E8%AF%8A%E6%89%80&src=vetmap&coordinate=gaode&callnative=1"},{"name":"关爱动物诊所(中街)","address":"河合村中街南2巷1号","phone":"15670962756","category":"医疗保健服务;动物医疗场所;宠物诊所","area":"","lng":112.60719,"lat":35.085405,"amap_id":"B0FFG52FG0","order":8,"prev_distance_km":1.37,"cumulative_distance_km":16.834,"amap_marker_url":"https://uri.amap.com/marker?position=112.607190,35.085405&name=%E5%85%B3%E7%88%B1%E5%8A%A8%E7%89%A9%E8%AF%8A%E6%89%80%28%E4%B8%AD%E8%A1%97%29&src=vetmap&coordinate=gaode&callnative=1"},{"name":"恒爱动物医院24h诊疗服务(济源总院)","address":"喜洋洋小区东南侧","phone":"16662936120","category":"医疗保健服务;动物医疗场所;宠物诊所","area":"","lng":112.615457,"lat":35.083503,"amap_id":"B0LGPHLDTO","order":9,"prev_distance_km":0.781,"cumulative_distance_km":17.615,"amap_marker_url":"https://uri.amap.com/marker?position=112.615457,35.083503&name=%E6%81%92%E7%88%B1%E5%8A%A8%E7%89%A9%E5%8C%BB%E9%99%A224h%E8%AF%8A%E7%96%97%E6%9C%8D%E5%8A%A1%28%E6%B5%8E%E6%BA%90%E6%80%BB%E9%99%A2%29&src=vetmap&coordinate=gaode&callnative=1"},{"name":"贝乐宠物医院","address":"宗庄家园南门旁","phone":"16613902521","category":"医疗保健服务;动物医疗场所;宠物诊所","area":"","lng":112.617047,"lat":35.060735,"amap_id":"B0ID4DOQ1L","order":10,"prev_distance_km":2.536,"cumulative_distance_km":20.151,"amap_marker_url":"https://uri.amap.com/marker?position=112.617047,35.060735&name=%E8%B4%9D%E4%B9%90%E5%AE%A0%E7%89%A9%E5%8C%BB%E9%99%A2&src=vetmap&coordinate=gaode&callnative=1"},{"name":"蓝天养殖技术服务部","address":"309省道北50米","phone":"13838918437","category":"医疗保健服务;动物医疗场所;兽医站","area":"","lng":112.606013,"lat":35.039409,"amap_id":"B0FFLE4FLP","order":11,"prev_distance_km":2.575,"cumulative_distance_km":22.726,"amap_marker_url":"https://uri.amap.com/marker?position=112.606013,35.039409&name=%E8%93%9D%E5%A4%A9%E5%85%BB%E6%AE%96%E6%8A%80%E6%9C%AF%E6%9C%8D%E5%8A%A1%E9%83%A8&src=vetmap&coordinate=gaode&callnative=1"},{"name":"宠福康动物诊所","address":"文昌路与玉川街交叉口东南80米","phone":"","category":"医疗保健服务;动物医疗场所;宠物诊所","area":"","lng":112.59336,"lat":35.071358,"amap_id":"B0IR0AV40Q","order":12,"prev_distance_km":3.735,"cumulative_distance_km":26.461,"amap_marker_url":"https://uri.amap.com/marker?position=112.593360,35.071358&name=%E5%AE%A0%E7%A6%8F%E5%BA%B7%E5%8A%A8%E7%89%A9%E8%AF%8A%E6%89%80&src=vetmap&coordinate=gaode&callnative=1"},{"name":"济源爱谛宠物医院","address":"大峪镇承留镇长基二号楼自东向西第二套","phone":"18839012008","category":"医疗保健服务;动物医疗场所;宠物诊所","area":"","lng":112.590712,"lat":35.075756,"amap_id":"B0LDO7PC7L","order":13,"prev_distance_km":0.545,"cumulative_distance_km":27.006,"amap_marker_url":"https://uri.amap.com/marker?position=112.590712,35.075756&name=%E6%B5%8E%E6%BA%90%E7%88%B1%E8%B0%9B%E5%AE%A0%E7%89%A9%E5%8C%BB%E9%99%A2&src=vetmap&coordinate=gaode&callnative=1"},{"name":"百灵动物医院","address":"济源大道长基四号楼底商220号","phone":"0391-6278120;17737338120;18103892120","category":"医疗保健服务;动物医疗场所;宠物诊所","area":"","lng":112.587611,"lat":35.076134,"amap_id":"B0FFFZ0GIN","order":14,"prev_distance_km":0.285,"cumulative_distance_km":27.291,"amap_marker_url":"https://uri.amap.com/marker?position=112.587611,35.076134&name=%E7%99%BE%E7%81%B5%E5%8A%A8%E7%89%A9%E5%8C%BB%E9%99%A2&src=vetmap&coordinate=gaode&callnative=1"},{"name":"友佳宠物医院(滨河南街)","address":"和景花园北门旁","phone":"0391-6047699;18603895597","category":"医疗保健服务;动物医疗场所;宠物诊所","area":"","lng":112.579457,"lat":35.082283,"amap_id":"B0FFGKDWL6","order":15,"prev_distance_km":1.009,"cumulative_distance_km":28.3,"amap_marker_url":"https://uri.amap.com/marker?position=112.579457,35.082283&name=%E5%8F%8B%E4%BD%B3%E5%AE%A0%E7%89%A9%E5%8C%BB%E9%99%A2%28%E6%BB%A8%E6%B2%B3%E5%8D%97%E8%A1%97%29&src=vetmap&coordinate=gaode&callnative=1"},{"name":"开心动物诊所","address":"龙潭路天坛花园","phone":"","category":"医疗保健服务;动物医疗场所;宠物诊所","area":"","lng":112.565809,"lat":35.097838,"amap_id":"B0FFFY1Y9L","order":16,"prev_distance_km":2.129,"cumulative_distance_km":30.43,"amap_marker_url":"https://uri.amap.com/marker?position=112.565809,35.097838&name=%E5%BC%80%E5%BF%83%E5%8A%A8%E7%89%A9%E8%AF%8A%E6%89%80&src=vetmap&coordinate=gaode&callnative=1"},{"name":"济牧兽药店","address":"承留大街与悠然路交叉口西160米","phone":"","category":"医疗保健服务;动物医疗场所;动物医疗场所","area":"","lng":112.489586,"lat":35.074696,"amap_id":"B0KRRRVU1W","order":17,"prev_distance_km":7.397,"cumulative_distance_km":37.827,"amap_marker_url":"https://uri.amap.com/marker?position=112.489586,35.074696&name=%E6%B5%8E%E7%89%A7%E5%85%BD%E8%8D%AF%E5%BA%97&src=vetmap&coordinate=gaode&callnative=1"},{"name":"康贝宠物诊所","address":"小浪底路172号","phone":"","category":"医疗保健服务;动物医疗场所;宠物诊所","area":"","lng":112.51902,"lat":34.923075,"amap_id":"B0M6DA61JV","order":18,"prev_distance_km":17.071,"cumulative_distance_km":54.898,"amap_marker_url":"https://uri.amap.com/marker?position=112.519020,34.923075&name=%E5%BA%B7%E8%B4%9D%E5%AE%A0%E7%89%A9%E8%AF%8A%E6%89%80&src=vetmap&coordinate=gaode&callnative=1"}]}